langgraph_deploy/__init__.py
langgraph_deploy/cli.py
langgraph_deploy/py.typed
langgraph_deploy-0.2.3.dist-info/licenses/LICENSE
langgraph_deploy-0.2.3.dist-info/METADATA
langgraph_deploy-0.2.3.dist-info/WHEEL
langgraph_deploy-0.2.3.dist-info/entry_points.txt
langgraph_deploy-0.2.3.dist-info/top_level.txt
langgraph_deploy-0.2.3.dist-info/RECORD
