Metadata-Version: 2.4
Name: langgraph-deploy
Version: 0.2.3
Summary: Adds a `deploy` subcommand to langgraph CLI to deploy Docker images to Cloud Run.
Author-email: neka-nat <nekanat.stock@gmail.com>
License: MIT
Requires-Python: >=3.10
License-File: LICENSE
Requires-Dist: typing-extensions>=4.8.0
Requires-Dist: langgraph-cli>=0.0.0
Dynamic: license-file
